cult_common/__init__.py
cult_common/config.py
cult_common/logging.py
cult_common/orm_models/__init__.py
cult_common/orm_models/timestamp_mixin.py
cult_common/orm_models/uuid_pk_mixin.py
cult_common/schemas/__init__.py
cult_common/schemas/raw_event.py
cult_common/schemas/signal.py
cult_common-0.2.0.dist-info/METADATA
cult_common-0.2.0.dist-info/WHEEL
cult_common-0.2.0.dist-info/top_level.txt
cult_common-0.2.0.dist-info/RECORD
